sgp/__init__.cpython-312-darwin.so
sgp/corr.py
sgp/io.cpython-312-darwin.so
sgp/version.cpython-312-darwin.so
sgp/decorators.cpython-312-darwin.so
sgp/app.cpython-312-darwin.so
sgp/config.cpython-312-darwin.so
sgp/__main__.cpython-312-darwin.so
sgp/pydantic.cpython-312-darwin.so
sgp/_version.cpython-312-darwin.so
sgp/figure.cpython-312-darwin.so
sgp/hashkey.cpython-312-darwin.so
sgp/ui/settings.cpython-312-darwin.so
sgp/ui/__init__.cpython-312-darwin.so
sgp/ui/application.cpython-312-darwin.so
sgp/ui/backend_qt.cpython-312-darwin.so
sgp/ui/mainwindow.cpython-312-darwin.so
sgp/ui/resource.cpython-312-darwin.so
sgp/ui/tabs/__init__.cpython-312-darwin.so
sgp/ui/tabs/hsstab.cpython-312-darwin.so
sgp/ui/tabs/querytab.cpython-312-darwin.so
sgp/ui/images/hss.png
sgp/ui/images/splash.png
sgp/ui/icons/chinese.png
sgp/ui/icons/logo.ico
sgp/ui/icons/save-as.png
sgp/ui/icons/github.png
sgp/ui/icons/logo.png
sgp/ui/icons/new.png
sgp/ui/icons/language.png
sgp/ui/icons/open.png
sgp/ui/icons/about.png
sgp/ui/icons/save.png
sgp/ui/icons/english.png
sgp/ui/icons/close.png
sgp/ui/templates/mpd.py.in
sgp/ui/widgets/__init__.cpython-312-darwin.so
sgp/ui/widgets/splashscreen.cpython-312-darwin.so
sgp/ui/widgets/propertywidget.cpython-312-darwin.so
sgp/ui/widgets/texwidget.cpython-312-darwin.so
sgp/ui/widgets/tabwidget.cpython-312-darwin.so
sgp/ui/widgets/tabwindow.cpython-312-darwin.so
sgp/ui/widgets/jupyterwidget.cpython-312-darwin.so
sgp/ui/widgets/scientificdoublespinbox.cpython-312-darwin.so
sgp/locales/sgp_zh_CN.qm
sgp/datasets/shanghai.crypt
sgp/models/__init__.cpython-312-darwin.so
sgp/models/mpd.cpython-312-darwin.so
sgp/models/base.cpython-312-darwin.so
sgp/models/ann.cpython-312-darwin.so
sgp/models/model.cpython-312-darwin.so
sgp/models/johnson.cpython-312-darwin.so
sgp/models/optimize/__init__.cpython-312-darwin.so
sgp/models/optimize/scipyoptimizer.cpython-312-darwin.so
sgp_gu-1.0.4.dist-info/RECORD
sgp_gu-1.0.4.dist-info/WHEEL
sgp_gu-1.0.4.dist-info/entry_points.txt
sgp_gu-1.0.4.dist-info/METADATA
sgp_gu-1.0.4.dist-info/licenses/LICENSE
